pronote/__init__.py
pronote/authentication.py
pronote/renderers.py
pronote/settings.py
pronote/urls.py
pronote/views.py
django_pronote-0.1.0.dist-info/LICENSE
django_pronote-0.1.0.dist-info/METADATA
django_pronote-0.1.0.dist-info/WHEEL
django_pronote-0.1.0.dist-info/top_level.txt
django_pronote-0.1.0.dist-info/RECORD
