Metadata-Version: 2.1
Name: django-pronote
Version: 0.1.0
Summary: Handle CAS login for Pronote (index éducation)
Home-page: https://github.com/briefmnews/django-pronote
Author: Brief.me
Author-email: tech@brief.me
License: GNU GPL v3
Platform: UNKNOWN
Classifier: Environment :: Web Environment
Classifier: Framework :: Django
Classifier: Framework :: Django :: 3.2
Classifier: Operating System :: OS Independent
Classifier: Programming Language :: Python
Classifier: Topic :: Software Development :: Libraries :: Python Modules
Classifier: Programming Language :: Python
Classifier: Programming Language :: Python :: 3
Classifier: Programming Language :: Python :: 3.9
Requires-Python: >=3.9
License-File: LICENSE
Requires-Dist: Django (>=3.2)
Requires-Dist: djangorestframework (>=3)
